helper20sms/__init__.py
helper20sms/exceptions.py
helper20sms/helper20sms.py
helper20sms-0.3.2.dist-info/LICENSE
helper20sms-0.3.2.dist-info/METADATA
helper20sms-0.3.2.dist-info/WHEEL
helper20sms-0.3.2.dist-info/top_level.txt
helper20sms-0.3.2.dist-info/RECORD
