Metadata-Version: 2.1
Name: helper20sms
Version: 0.3.2
Summary: HelperSMS API wrapper for Python
Home-page: https://github.com/HelperSMS/helper20sms
Author: HelperSMS
Author-email: admin@helper20sms.ru
License: MIT License
Project-URL: Documentation, https://api.helper20sms.ru/docs
Requires-Python: >=3.9
License-File: LICENSE
Requires-Dist: aiohttp ~=3.9.1
Requires-Dist: typing ~=3.7.4.3
Requires-Dist: requests ~=2.31.0
